README.md
setup.py
py3pdb/__init__.py
py3pdb/data.py
py3pdb/download.py
py3pdb/search.py
py3pdb/utils.py
py3pdb.egg-info/PKG-INFO
py3pdb.egg-info/SOURCES.txt
py3pdb.egg-info/dependency_links.txt
py3pdb.egg-info/requires.txt
py3pdb.egg-info/top_level.txt